{
    "Metadata": {
        "Author": "clorton",
        "DateCreated": "Mon Mar 10 05:17:00 2014",
        "NodeCount": 11,
        "Tool": "manual"
    },
    "Nodes": [
        {
            "NodeID": 1487548419, 
            "NodeAttributes": {
                "Latitude": 12.4208, 
                "Longitude": 9.15417
            }
        }, 
        {
            "NodeID": 1487613955, 
            "NodeAttributes": {
                "Latitude": 12.4208, 
                "Longitude": 9.1625
            }
        }, 
        {
            "NodeID": 1487679488, 
            "NodeAttributes": {
                "Latitude": 12.3958, 
                "Longitude": 9.17084
            }
        }, 
        {
            "NodeID": 1487679489, 
            "NodeAttributes": {
                "Latitude": 12.4042, 
                "Longitude": 9.17084
            }
        }, 
        {
            "NodeID": 1487679490, 
            "NodeAttributes": {
                "Latitude": 12.4125, 
                "Longitude": 9.17084
            }
        }, 
        {
            "NodeID": 1487679491, 
            "NodeAttributes": {
                "Latitude": 12.4208, 
                "Longitude": 9.17084
            }
        }, 
        {
            "NodeID": 1487679492, 
            "NodeAttributes": {
                "Latitude": 12.4292, 
                "Longitude": 9.17084
            }
        }, 
        {
            "NodeID": 1487679493, 
            "NodeAttributes": {
                "Latitude": 12.4375, 
                "Longitude": 9.17084
            }
        }, 
        {
            "NodeID": 1487679494, 
            "NodeAttributes": {
                "Latitude": 12.4458, 
                "Longitude": 9.17084
            }
        }, 
        {
            "NodeID": 1487745027, 
            "NodeAttributes": {
                "Latitude": 12.4208, 
                "Longitude": 9.17917
            }
        }, 
        {
            "NodeID": 1487810563, 
            "NodeAttributes": {
                "Latitude": 12.4208, 
                "Longitude": 9.1875
            }
        }
     ]
}